setup.py
gachengoh_distributions/Binomialdistribution.py
gachengoh_distributions/Gaussiandistribution.py
gachengoh_distributions/Generaldistribution.py
gachengoh_distributions/__init__.py
gachengoh_distributions.egg-info/PKG-INFO
gachengoh_distributions.egg-info/SOURCES.txt
gachengoh_distributions.egg-info/dependency_links.txt
gachengoh_distributions.egg-info/not-zip-safe
gachengoh_distributions.egg-info/top_level.txt