Metadata-Version: 1.0
Name: gachengoh-distributions
Version: 1.2
Summary: Gaussian distributions
Home-page: UNKNOWN
Author: Tyller Gachengo
Author-email: gachengomarugu@gmail.com
License: UNKNOWN
Platform: UNKNOWN
